boot_dw/__init__.py
boot_dw/bootstrap.py
boot_dw/core.py
boot_dw/tests.py
boot_dw/utils.py
boot_dw-0.0.1.dist-info/licenses/LICENSE
boot_dw-0.0.1.dist-info/METADATA
boot_dw-0.0.1.dist-info/WHEEL
boot_dw-0.0.1.dist-info/top_level.txt
boot_dw-0.0.1.dist-info/RECORD
